jupyter_reorder_python_imports/__init__.py
jupyter_reorder_python_imports/jupyter_reorder_python_imports.py
jupyter_reorder_python_imports-0.0.2.dist-info/LICENSE
jupyter_reorder_python_imports-0.0.2.dist-info/METADATA
jupyter_reorder_python_imports-0.0.2.dist-info/WHEEL
jupyter_reorder_python_imports-0.0.2.dist-info/RECORD
