Metadata-Version: 2.1
Name: jupyter-reorder-python-imports
Version: 0.0.2
Summary: Reorder python imports for Jupyter notebook and lab
Home-page: https://github.com/Stoops-ML/jupyter-reorder-python-imports
License: MIT
Author: Daniel Stoops
Author-email: danielstoops25@gmail.com
Maintainer: Daniel Stoops
Maintainer-email: danielstoops25@gmail.com
Requires-Python: >=3.8.1,<4.0.0
Classifier: License :: OSI Approved :: MIT License
Classifier: Programming Language :: Python :: 3
Classifier: Programming Language :: Python :: 3.9
Classifier: Programming Language :: Python :: 3.10
Classifier: Programming Language :: Python :: 3.11
Classifier: Programming Language :: Python :: 3 :: Only
Classifier: Programming Language :: Python :: 3.8
Requires-Dist: reorder-python-imports (>=3.10.0,<4.0.0)
